mongo_manager/__init__.py
mongo_manager/exceptions.py
mongo_manager/mongo_manager.py
mongo_manager/mongo_utils.py
mongo_manager/aggregations/__init__.py
mongo_manager/aggregations/agg_op_comparator.py
mongo_manager/aggregations/agg_op_logical.py
mongo_manager/aggregations/agg_op_operators.py
mongo_manager/aggregations/agg_op_regex.py
mongo_manager/aggregations/aggregation.py
mongo_manager/aggregations/aggregation_decorators.py
mongo_manager/aggregations/aggregation_functions.py
mongo_manager/aggregations/aggregation_stages.py
mongo_manager/aggregations/agreggation_operations.py
mongo_manager/aggregations/utils_name.py
mongo_manager/entity/__init__.py
mongo_manager/entity/objeto_mongo_abstract.py
mongo_manager/patrones/__init__.py
mongo_manager/patrones/singleton.py
mongo_manager/repository/__init__.py
mongo_manager/repository/repository_base.py
mongo_manager_juan_palma_borda-0.9.7.dist-info/LICENSE
mongo_manager_juan_palma_borda-0.9.7.dist-info/LICENSE.txt
mongo_manager_juan_palma_borda-0.9.7.dist-info/METADATA
mongo_manager_juan_palma_borda-0.9.7.dist-info/WHEEL
mongo_manager_juan_palma_borda-0.9.7.dist-info/top_level.txt
mongo_manager_juan_palma_borda-0.9.7.dist-info/RECORD
