Metadata-Version: 2.1
Name: mongo-manager-juan-palma-borda
Version: 0.9.7
Summary: Libreria para manejar objetos almacenados en MongoDB, usando la referencia de los CRUDRepository de SpringBoot
Home-page: https://github.com/muerterauda/mongo_manager
Author: Juan Palma Borda
Author-email: Juan Palma Borda <juanpalmaborda@hotmail.com>
Keywords: mongodb,pymongo,mongo_manager
Classifier: Programming Language :: Python :: 3
Requires-Python: >=3.7
License-File: LICENSE
License-File: LICENSE.txt
Requires-Dist: pymongo >=3.12.1
